{
  "_meta": {
    "last_stream_check": "2026-06-15T14:15:54.420331+00:00"
  },
  "assignment_412444": {
    "id": "assignment_412444",
    "raw_id": 412444,
    "course_id": 87136,
    "course": "电工学实验",
    "title": "大作业报告",
    "type": "作业",
    "due": "2026-06-21T15:59:59Z",
    "remind_at": "2026-06-21T13:59:59+00:00",
    "reminded": false,
    "submitted": false
  },
  "assignment_413440": {
    "id": "assignment_413440",
    "raw_id": 413440,
    "course_id": 86626,
    "course": "信息素养与实践",
    "title": "期末小组作业：文献调研报告",
    "type": "作业",
    "due": "2026-06-16T15:59:59Z",
    "remind_at": "2026-06-16T13:59:59+00:00",
    "reminded": false,
    "submitted": true
  },
  "assignment_393715": {
    "id": "assignment_393715",
    "raw_id": 393715,
    "course_id": 87742,
    "course": "信号与系统设计",
    "title": "Lab5",
    "type": "作业",
    "due": "2026-07-05T15:59:00Z",
    "remind_at": "2026-07-05T13:59:00+00:00",
    "reminded": false,
    "submitted": false
  },
  "assignment_414912": {
    "id": "assignment_414912",
    "raw_id": 414912,
    "course_id": 87049,
    "course": "大学物理(A类）（3）",
    "title": "第七次作业",
    "type": "作业",
    "due": "2026-06-18T15:59:59Z",
    "remind_at": "2026-06-18T13:59:59+00:00",
    "reminded": false,
    "submitted": false
  },
  "assignment_415054": {
    "id": "assignment_415054",
    "raw_id": 415054,
    "course_id": 89372,
    "course": "形势与政策",
    "title": "期末考核",
    "type": "作业",
    "due": "2026-06-21T15:59:59Z",
    "remind_at": "2026-06-21T13:59:59+00:00",
    "reminded": false,
    "submitted": false
  }
}